{
  "Header": [
    {
      "status": "Success",
      "request_time": "2025-11-20T00:14:08-05:00",
      "rows": 2
    }
  ],
  "Data": [
    {
      "state_code": "49",
      "county_code": "011",
      "site_number": "0004",
      "parameter_code": "61101",
      "poc": 1,
      "latitude": 40.902967,
      "longitude": -111.884467,
      "datum": "WGS84",
      "parameter": "Wind Speed - Scalar",
      "sample_duration_code": "1",
      "sample_duration": "1 HOUR",
      "pollutant_standard": null,
      "metric_used": "Observed Values",
      "method": "Instrumental - RM Young Ultrasonic Anemometer Model 86004",
      "year": 2025,
      "units_of_measure": "Knots",
      "event_type": "No Events",
      "observation_count": 7265,
      "observation_percent": 83.0,
      "validity_indicator": "Y",
      "valid_day_count": 301,
      "required_day_count": 365,
      "exceptional_data_count": 0,
      "null_observation_count": 31,
      "primary_exceedance_count": null,
      "secondary_exceedance_count": null,
      "certification_indicator": "Certification not required",
      "arithmetic_mean": 3.710365,
      "standard_deviation": 2.573538,
      "first_max_value": 17.6,
      "first_max_datetime": "2025-02-07 09:00",
      "second_max_value": 17.4,
      "second_max_datetime": "2025-02-07 08:00",
      "third_max_value": 17.1,
      "third_max_datetime": "2025-02-05 04:00",
      "fourth_max_value": 16.8,
      "fourth_max_datetime": "2025-02-05 03:00",
      "first_max_nonoverlap_value": null,
      "first_max_n_o_datetime": null,
      "second_max_nonoverlap_value": null,
      "second_max_n_o_datetime": null,
      "ninety_ninth_percentile": 13.1,
      "ninety_eighth_percentile": 11.6,
      "ninety_fifth_percentile": 9.2,
      "ninetieth_percentile": 7.3,
      "seventy_fifth_percentile": 4.5,
      "fiftieth_percentile": 3.0,
      "tenth_percentile": 1.5,
      "local_site_name": "Bountiful Viewmont",
      "site_address": "171 WEST 1370 NORTH, BOUNTIFUL, UTAH",
      "state": "Utah",
      "county": "Davis",
      "city": "Bountiful",
      "cbsa_code": "36260",
      "cbsa": "Ogden-Clearfield, UT",
      "date_of_last_change": "2025-11-19"
    },
    {
      "state_code": "49",
      "county_code": "011",
      "site_number": "6001",
      "parameter_code": "61101",
      "poc": 1,
      "latitude": 41.041609,
      "longitude": -112.233281,
      "datum": "WGS84",
      "parameter": "Wind Speed - Scalar",
      "sample_duration_code": "1",
      "sample_duration": "1 HOUR",
      "pollutant_standard": null,
      "metric_used": "Observed Values",
      "method": "INSTRUMENTAL - ELECTRONIC OR MACHINE AVG.",
      "year": 2025,
      "units_of_measure": "Knots",
      "event_type": "No Events",
      "observation_count": 6530,
      "observation_percent": 75.0,
      "validity_indicator": "Y",
      "valid_day_count": 271,
      "required_day_count": 365,
      "exceptional_data_count": 0,
      "null_observation_count": 22,
      "primary_exceedance_count": null,
      "secondary_exceedance_count": null,
      "certification_indicator": "Certification not required",
      "arithmetic_mean": 6.910276,
      "standard_deviation": 4.282505,
      "first_max_value": 30.1,
      "first_max_datetime": "2025-05-12 19:00",
      "second_max_value": 30.0,
      "second_max_datetime": "2025-06-20 22:00",
      "third_max_value": 29.6,
      "third_max_datetime": "2025-02-05 02:00",
      "fourth_max_value": 29.5,
      "fourth_max_datetime": "2025-05-12 16:00",
      "first_max_nonoverlap_value": null,
      "first_max_n_o_datetime": null,
      "second_max_nonoverlap_value": null,
      "second_max_n_o_datetime": null,
      "ninety_ninth_percentile": 23.1,
      "ninety_eighth_percentile": 19.8,
      "ninety_fifth_percentile": 15.9,
      "ninetieth_percentile": 12.7,
      "seventy_fifth_percentile": 8.2,
      "fiftieth_percentile": 5.7,
      "tenth_percentile": 3.0,
      "local_site_name": "Antelope Island",
      "site_address": "(NO STREET ADDRESS; ON ISLAND)",
      "state": "Utah",
      "county": "Davis",
      "city": null,
      "cbsa_code": "36260",
      "cbsa": "Ogden-Clearfield, UT",
      "date_of_last_change": "2025-10-28"
    }
  ]
}
